pushcart/__init__.py
pushcart/log_handlers/__init__.py
pushcart/log_handlers/app_insights_handler.py
pushcart/metadata/__init__.py
pushcart/metadata/metadata.py
pushcart/metadata/spark.py
pushcart/py.typed
pushcart/sources/__init__.py
pushcart/sources/rest_api.py
pushcart/utils.py
pushcart-1.7.5.dist-info/LICENSE.txt
pushcart-1.7.5.dist-info/METADATA
pushcart-1.7.5.dist-info/WHEEL
pushcart-1.7.5.dist-info/RECORD
