Metadata-Version: 2.1
Name: pushcart
Version: 1.7.5
Summary: Metadata transformations for Spark
License: Apache-2.0
Author: Victor Blaga
Author-email: victor.blaga@revodata.nl
Requires-Python: >=3.10,<4.0
Classifier: License :: OSI Approved :: Apache Software License
Classifier: Operating System :: OS Independent
Classifier: Programming Language :: Python :: 3
Classifier: Programming Language :: Python :: 3.10
Classifier: Programming Language :: Python :: 3.11
Classifier: Programming Language :: Python :: 3.12
Classifier: Topic :: Database :: Database Engines/Servers
Classifier: Topic :: Software Development :: Libraries :: Application Frameworks
Classifier: Topic :: Software Development :: Libraries :: Python Modules
Requires-Dist: authlib (>=1.3.0,<2.0.0)
Requires-Dist: azure-monitor-opentelemetry (>=1.4.0,<2.0.0)
Requires-Dist: delta-spark (>=3.1.0,<4.0.0)
Requires-Dist: httpx (>=0.27.0,<0.28.0)
Requires-Dist: loguru (>=0.7.2,<0.8.0)
Requires-Dist: mkdocstrings[python] (>=0.25.1,<0.26.0)
Requires-Dist: opentelemetry-sdk (>=1.24.0,<2.0.0)
Requires-Dist: python-dotenv (>=1.0.1,<2.0.0)
Requires-Dist: validators (>=0.28.1,<0.29.0)
